llama_index/utils/workflow/__init__.py
llama_index_utils_workflow-0.8.0.dist-info/WHEEL
llama_index_utils_workflow-0.8.0.dist-info/METADATA
llama_index_utils_workflow-0.8.0.dist-info/RECORD
