Metadata-Version: 2.3
Name: llama-index-utils-workflow
Version: 0.8.0
Summary: llama-index utils for workflows
Author: Adrian Lyjak
Author-email: Adrian Lyjak <adrianlyjak@gmail.com>
Requires-Dist: llama-index-core>=0.14,<0.15.0
Requires-Dist: llama-index-workflows>=2.12.0,<3.0.0
Requires-Dist: pyvis>=0.3.2
Requires-Python: >=3.9
